badlon/block_gene_match.py
badlon/blocks_analysis.py
badlon/prepare_data_for_sibeliaz.py
badlon/run_badlon.py
badlon/charts/coverage.py
badlon/charts/inter_block_distribution.py
badlon/charts/length_distribution.py
badlon/charts/pan_genome.py
badlon/charts/u_curve.py
badlon/data/converters.py
badlon/data/coverage.py
badlon/data/parsers.py
badlon/data/process.py
badlon-0.1.4.dist-info/LICENSE
badlon-0.1.4.dist-info/METADATA
badlon-0.1.4.dist-info/WHEEL
badlon-0.1.4.dist-info/entry_points.txt
badlon-0.1.4.dist-info/top_level.txt
badlon-0.1.4.dist-info/RECORD
